iree/turbine/__init__.py
shark_turbine/aot/__init__.py
shark_turbine/aot/compiled_module.py
shark_turbine/aot/decompositions.py
shark_turbine/aot/exporter.py
shark_turbine/aot/fx_programs.py
shark_turbine/aot/params.py
shark_turbine/aot/tensor_traits.py
shark_turbine/aot/builtins/__init__.py
shark_turbine/aot/builtins/globals.py
shark_turbine/aot/builtins/jittable.py
shark_turbine/aot/passes/__init__.py
shark_turbine/aot/passes/functorch.py
shark_turbine/aot/support/ir_utils.py
shark_turbine/aot/support/procedural/__init__.py
shark_turbine/aot/support/procedural/base.py
shark_turbine/aot/support/procedural/exported_program.py
shark_turbine/aot/support/procedural/globals.py
shark_turbine/aot/support/procedural/iree_emitter.py
shark_turbine/aot/support/procedural/primitives.py
shark_turbine/aot/support/procedural/tracer.py
shark_turbine/dynamo/__init__.py
shark_turbine/dynamo/decompositions.py
shark_turbine/dynamo/executor.py
shark_turbine/dynamo/passes.py
shark_turbine/dynamo/tensor.py
shark_turbine/dynamo/type_conversion.py
shark_turbine/dynamo/backends/cpu.py
shark_turbine/importers/ir.py
shark_turbine/importers/utils.py
shark_turbine/kernel/__init__.py
shark_turbine/kernel/_support/context.py
shark_turbine/kernel/_support/dtype.py
shark_turbine/kernel/_support/indexing.py
shark_turbine/kernel/_support/regions.py
shark_turbine/kernel/_support/shaped_type.py
shark_turbine/kernel/_support/tracing.py
shark_turbine/kernel/compiler/base.py
shark_turbine/kernel/compiler/builder.py
shark_turbine/kernel/compiler/dispatch_codegen.py
shark_turbine/kernel/compiler/host_codegen.py
shark_turbine/kernel/compiler/ir.py
shark_turbine/kernel/compiler/kernel_codegen.py
shark_turbine/kernel/compiler/op_matchers.py
shark_turbine/kernel/compiler/utils.py
shark_turbine/kernel/compiler/vector_codegen.py
shark_turbine/kernel/gen/__init__.py
shark_turbine/kernel/gen/kernel.py
shark_turbine/kernel/gen/thread.py
shark_turbine/kernel/lang/__init__.py
shark_turbine-2.4.1.dist-info/LICENSE
shark_turbine-2.4.1.dist-info/METADATA
shark_turbine-2.4.1.dist-info/WHEEL
shark_turbine-2.4.1.dist-info/entry_points.txt
shark_turbine-2.4.1.dist-info/top_level.txt
shark_turbine-2.4.1.dist-info/RECORD
