Metadata-Version: 2.1
Name: shark-turbine
Version: 2.4.1
Summary: SHARK Turbine Machine Learning Deployment Tools
Home-page: https://github.com/nod-ai/SHARK-Turbine
Author: SHARK Authors
Author-email: stella@nod.ai
License: Apache-2.0
Classifier: Development Status :: 5 - Production/Stable
Classifier: License :: OSI Approved :: Apache Software License
Classifier: Programming Language :: Python :: 3
License-File: LICENSE
Requires-Dist: numpy>=1.26.3
Requires-Dist: iree-compiler
Requires-Dist: iree-runtime
Requires-Dist: torch>=2.3.0
Requires-Dist: Jinja2>=3.1.3
Provides-Extra: testing
Requires-Dist: pytest>=8.0.0; extra == "testing"
Requires-Dist: pytest-xdist>=3.5.0; extra == "testing"
Requires-Dist: parameterized>=0.9.0; extra == "testing"
